pystack.py
pystack_debugger_custom-0.10.0.dist-info/LICENSE
pystack_debugger_custom-0.10.0.dist-info/METADATA
pystack_debugger_custom-0.10.0.dist-info/WHEEL
pystack_debugger_custom-0.10.0.dist-info/entry_points.txt
pystack_debugger_custom-0.10.0.dist-info/top_level.txt
pystack_debugger_custom-0.10.0.dist-info/RECORD
